ptemcee/__init__.py
ptemcee/interruptible_pool.py
ptemcee/mpi_pool.py
ptemcee/sampler.py
ptemcee/tests.py
ptemcee/util.py
ptemcee_for_orbitize-1.0.0.dist-info/LICENSE
ptemcee_for_orbitize-1.0.0.dist-info/METADATA
ptemcee_for_orbitize-1.0.0.dist-info/WHEEL
ptemcee_for_orbitize-1.0.0.dist-info/top_level.txt
ptemcee_for_orbitize-1.0.0.dist-info/RECORD
