Metadata-Version: 2.1
Name: ptemcee-for-orbitize
Version: 1.0.0
Summary: Parallel-tempered emcee.
Home-page: https://github.com/willvousden/ptemcee
Download-URL: https://github.com/willvousden/ptemcee/tarball/1.0.0
Author: Will Vousden
Author-email: will@vousden.me.uk
License: MIT
Classifier: Development Status :: 5 - Production/Stable
Classifier: Intended Audience :: Developers
Classifier: Intended Audience :: Science/Research
Classifier: License :: OSI Approved :: MIT License
Classifier: Operating System :: OS Independent
Classifier: Programming Language :: Python
License-File: LICENSE
Requires-Dist: numpy
